PyxDistributions/Binomialdistribution.py
PyxDistributions/Gaussiandistribution.py
PyxDistributions/Generaldistribution.py
PyxDistributions/__init__.py
PyxDistributions-1.0.0.dist-info/METADATA
PyxDistributions-1.0.0.dist-info/WHEEL
PyxDistributions-1.0.0.dist-info/license.txt
PyxDistributions-1.0.0.dist-info/top_level.txt
PyxDistributions-1.0.0.dist-info/RECORD
